Metadata-Version: 1.1
Name: AsyncParse
Version: 0.0.5
Summary: AsyncParse is a library allowing you to make multiple http requests asynchronously
Home-page: UNKNOWN
Author: Mironov Mihail
Author-email: devborokoko@gmail.com
License: MIT
Keywords: webscraping
Platform: UNKNOWN
Classifier: Development Status :: 5 - Production/Stable
Classifier: Intended Audience :: Education
Classifier: License :: OSI Approved :: MIT License
Classifier: Programming Language :: Python :: 3
